{
    "id": "65ff72dcf1aa1b9c009c1993",
    "user": "moh70@pitt.edu",
    "name": "File Handling",
    "items": [
        {
            "item": "65ff6de7f1aa1b9c009c1931",
            "type": "example",
            "details": {
                "name": "CopyFileTo",
                "description": "A Java program that demonstrate copying a text file."
            }
        },
        {
            "item": "65ff6f6bf1aa1b9c009c1965",
            "type": "challenge",
            "details": {
                "name": "PrintFileContent",
                "description": "Read and print the contents of a text file."
            }
        }
    ]
}